README.md
setup.py
simsimsim/Indices.py
simsimsim/Raos.py
simsimsim/Visualize.py
simsimsim/__init__.py
simsimsim.egg-info/PKG-INFO
simsimsim.egg-info/SOURCES.txt
simsimsim.egg-info/dependency_links.txt
simsimsim.egg-info/requires.txt
simsimsim.egg-info/top_level.txt